rho_django_user-1.0.0.dist-info/DESCRIPTION.rst
rho_django_user-1.0.0.dist-info/METADATA
rho_django_user-1.0.0.dist-info/RECORD
rho_django_user-1.0.0.dist-info/WHEEL
rho_django_user-1.0.0.dist-info/metadata.json
rho_django_user-1.0.0.dist-info/top_level.txt
rhouser/__init__.py
rhouser/admin.py
rhouser/apps.py
rhouser/forms.py
rhouser/models.py
rhouser/migrations/0001_initial.py
rhouser/migrations/__init__.py
rhouser/tests/__init__.py
rhouser/tests/test_auth_backends.py
rhouser/tests/test_forms.py
rhouser/tests/test_models.py
